[
  {
    "CHF": {
      "r030": 756,
      "txt": "Швейцарський франк",
      "rate": 3.195592,
      "cc": "CHF",
      "exchangedate": "29.11.2001"
    }
  },
  {
    "EUR": {
      "r030": 978,
      "txt": "Євро",
      "rate": 4.66109,
      "cc": "EUR",
      "exchangedate": "29.11.2001"
    }
  },
  {
    "EUR": {
      "r030": 978,
      "txt": "Євро",
      "rate": 4.636549,
      "cc": "EUR",
      "exchangedate": "28.11.2001"
    }
  },
  {
    "USD": {
      "r030": 840,
      "txt": "Долар США",
      "rate": 5.276,
      "cc": "USD",
      "exchangedate": "28.11.2001"
    }
  },
  {
    "CHF": {
      "r030": 756,
      "txt": "Швейцарський франк",
      "rate": 3.166825,
      "cc": "CHF",
      "exchangedate": "28.11.2001"
    }
  }
]
