[
  {
    "EUR": {
      "r030": 978,
      "txt": "Євро",
      "rate": 4.688102,
      "cc": "EUR",
      "exchangedate": "11.04.2002"
    }
  },
  {
    "EUR": {
      "r030": 978,
      "txt": "Євро",
      "rate": 4.669452,
      "cc": "EUR",
      "exchangedate": "10.04.2002"
    }
  },
  {
    "CHF": {
      "r030": 756,
      "txt": "Швейцарський франк",
      "rate": 3.184079,
      "cc": "CHF",
      "exchangedate": "10.04.2002"
    }
  },
  {
    "USD": {
      "r030": 840,
      "txt": "Долар США",
      "rate": 5.3286,
      "cc": "USD",
      "exchangedate": "10.04.2002"
    }
  }
]
