[
  {
    "EUR": {
      "r030": 978,
      "txt": "Євро",
      "rate": 22.934148,
      "cc": "EUR",
      "exchangedate": "30.05.2015"
    }
  },
  {
    "USD": {
      "r030": 840,
      "txt": "Долар США",
      "rate": 21.048227,
      "cc": "USD",
      "exchangedate": "30.05.2015"
    }
  },
  {
    "CHF": {
      "r030": 756,
      "txt": "Швейцарський франк",
      "rate": 22.17145,
      "cc": "CHF",
      "exchangedate": "29.05.2015"
    }
  },
  {
    "CHF": {
      "r030": 756,
      "txt": "Швейцарський франк",
      "rate": 22.17145,
      "cc": "CHF",
      "exchangedate": "30.05.2015"
    }
  },
  {
    "EUR": {
      "r030": 978,
      "txt": "Євро",
      "rate": 22.934148,
      "cc": "EUR",
      "exchangedate": "29.05.2015"
    }
  },
  {
    "USD": {
      "r030": 840,
      "txt": "Долар США",
      "rate": 21.048227,
      "cc": "USD",
      "exchangedate": "29.05.2015"
    }
  }
]
